euchre/__init__.py
euchre/__main__.py
euchre/cli.py
euchre/gui.py
euchre/tests/__init__.py
euchre/tests/conftest.py
euchre/tests/test_utils.py
euchre/utils.py
euchre-0.0.dist-info/LICENSE.md
euchre-0.0.dist-info/WHEEL
euchre-0.0.dist-info/METADATA
euchre-0.0.dist-info/RECORD
